Metadata-Version: 2.4
Name: backports.lzma-defi-corrected
Version: 0.0.14
Summary: Backport of Python 3.3's 'lzma' module for XZ/LZMA compressed files. (defi corrected version)
Home-page: https://github.com/peterjc/backports.lzma
Author: Peter Cock, based on work by Nadeem Vawda and Per Oyvind Karlsen
Author-email: p.j.a.cock@googlemail.com
License: 3-clause BSD License
Keywords: xz lzma compression decompression
Classifier: Development Status :: 5 - Production/Stable
Classifier: Programming Language :: Python
Classifier: Programming Language :: Python :: 2.6
Classifier: Programming Language :: Python :: 2.7
Classifier: Programming Language :: Python :: 3.6
Classifier: Programming Language :: Python :: 3.7
Classifier: Topic :: Software Development :: Libraries :: Python Modules
Classifier: Intended Audience :: Developers
Classifier: License :: OSI Approved :: BSD License
Classifier: Topic :: System :: Archiving :: Compression
Dynamic: author
Dynamic: author-email
Dynamic: classifier
Dynamic: description
Dynamic: home-page
Dynamic: keywords
Dynamic: license
Dynamic: summary
